langflow/version/__init__.py
langflow/version/version.py
mseep_langflow-1.6.3.dist-info/METADATA
mseep_langflow-1.6.3.dist-info/WHEEL
mseep_langflow-1.6.3.dist-info/entry_points.txt
mseep_langflow-1.6.3.dist-info/licenses/LICENSE
mseep_langflow-1.6.3.dist-info/RECORD
